{
  "reviews": [{
    "reviewer": {
      "displayName": "Damián De Laurentis"
    },
    "starRating": "FIVE",
    "comment": "Buena atención\n\n(Translated by Google)\nGood service",
    "createTime": "2017-03-22T11:14:52.737Z",
    "updateTime": "2020-01-10T21:45:31.191592Z",
    "name": "accounts/109853746269412609224/locations/10695122331646821595/reviews/ChZDSUhNMG9nS0VJQ0FnSURRbU1YdVRnEAE"
  }, {
    "reviewer": {
      "displayName": "mauro lendaro"
    },
    "starRating": "FIVE",
    "createTime": "2020-01-10T14:23:24.247045Z",
    "updateTime": "2020-01-10T14:23:24.247045Z",
    "name": "accounts/109853746269412609224/locations/10695122331646821595/reviews/ChZDSUhNMG9nS0VJQ0FnSURNbzRXY0xREAE"
  }, {
    "reviewer": {
      "displayName": "Paul Eduardo Asis"
    },
    "starRating": "FIVE",
    "createTime": "2020-01-08T23:30:42.069854Z",
    "updateTime": "2020-01-08T23:30:42.069854Z",
    "name": "accounts/109853746269412609224/locations/10695122331646821595/reviews/ChdDSUhNMG9nS0VJQ0FnSURNM2ZEZXRBRRAB"
  }, {
    "reviewer": {
      "displayName": "maria isabel estevez"
    },
    "starRating": "THREE",
    "comment": "Buena atención. Pero no reciben serviclub.\n\n(Translated by Google)\nGood service. But they don\u0027t accept Serviclub.",
    "createTime": "2020-01-08T18:57:42.998980Z",
    "updateTime": "2020-01-08T18:57:42.998980Z",
    "name": "accounts/109853746269412609224/locations/10695122331646821595/reviews/ChdDSUhNMG9nS0VJQ0FnSURNblk2eXVnRRAB"
  }, {
    "reviewer": {
      "displayName": "Silvia Pujadas"
    },
    "starRating": "FOUR",
    "createTime": "2020-01-08T18:11:31.550081Z",
    "updateTime": "2020-01-08T18:11:31.550081Z",
    "name": "accounts/109853746269412609224/locations/10695122331646821595/reviews/ChdDSUhNMG9nS0VJQ0FnSURNbllxSmtnRRAB"
  }, {
    "reviewer": {
      "displayName": "claudia segovia"
    },
    "starRating": "FIVE",
    "createTime": "2020-01-08T12:17:45.436264Z",
    "updateTime": "2020-01-08T12:17:45.436264Z",
    "name": "accounts/109853746269412609224/locations/10695122331646821595/reviews/ChdDSUhNMG9nS0VJQ0FnSURNN2FMYmpRRRAB"
  }, {
    "reviewer": {
      "displayName": "Maximiliano Werenitzky"
    },
    "starRating": "FIVE",
    "createTime": "2020-01-08T04:18:25.499357Z",
    "updateTime": "2020-01-08T04:18:25.499357Z",
    "name": "accounts/109853746269412609224/locations/10695122331646821595/reviews/ChdDSUhNMG9nS0VJQ0FnSURNcmRUcGdBRRAB"
  }, {
    "reviewer": {
      "displayName": "jorge 223"
    },
    "starRating": "FIVE",
    "comment": "Todo bien como toda YPF, y se puede pagar con la aplicación del celular de YPF\n\n(Translated by Google)\nEverything is fine, as with all YPF stations, and you can pay with the YPF mobile app.",
    "createTime": "2020-01-07T23:40:07.376786Z",
    "updateTime": "2020-01-07T23:40:07.376786Z",
    "name": "accounts/109853746269412609224/locations/10695122331646821595/reviews/ChdDSUhNMG9nS0VJQ0FnSURNemZudjRBRRAB"
  }, {
    "reviewer": {
      "displayName": "D L"
    },
    "starRating": "THREE",
    "createTime": "2020-01-04T19:05:56.610612Z",
    "updateTime": "2020-01-04T19:05:56.610612Z",
    "name": "accounts/109853746269412609224/locations/10695122331646821595/reviews/ChZDSUhNMG9nS0VJQ0FnSURNMlpuS05nEAE"
  }, {
    "reviewer": {
      "displayName": "Maria Rosa Jauregui"
    },
    "starRating": "FOUR",
    "comment": "Tiene servicio de comidas y se ve muy bueno\n\n(Translated by Google)\nIt has food service and it looks very good",
    "createTime": "2019-12-29T13:43:57.392674Z",
    "updateTime": "2019-12-29T13:43:57.392674Z",
    "name": "accounts/109853746269412609224/locations/10695122331646821595/reviews/ChdDSUhNMG9nS0VJQ0FnSURNdHFhWDJnRRAB"
  }, {
    "reviewer": {
      "displayName": "facundo coronel"
    },
    "starRating": "THREE",
    "comment": "Que se yo. Me cargaron nafta bien!!\n\n(Translated by Google)\nWhat do I know? They filled me up with gas!",
    "createTime": "2019-12-29T03:14:32.237751Z",
    "updateTime": "2019-12-29T03:14:32.237751Z",
    "name": "accounts/109853746269412609224/locations/10695122331646821595/reviews/ChZDSUhNMG9nS0VJQ0FnSURNbHFXWEtREAE"
  }, {
    "reviewer": {
      "displayName": "Enrique Navarro"
    },
    "starRating": "FOUR",
    "comment": "Se espera mucho más\n\n(Translated by Google)\nMuch more is expected.",
    "createTime": "2019-12-27T20:58:41.899403Z",
    "updateTime": "2019-12-27T20:58:41.899403Z",
    "name": "accounts/109853746269412609224/locations/10695122331646821595/reviews/ChdDSUhNMG9nS0VJQ0FnSURNLXFPdm1RRRAB"
  }, {
    "reviewer": {
      "displayName": "Hernan Sellaro"
    },
    "starRating": "FIVE",
    "createTime": "2019-12-25T23:36:41.043385Z",
    "updateTime": "2019-12-25T23:36:41.043385Z",
    "name": "accounts/109853746269412609224/locations/10695122331646821595/reviews/ChdDSUhNMG9nS0VJQ0FnSURNeXRfOWdnRRAB"
  }, {
    "reviewer": {
      "displayName": "Damian Fernandez"
    },
    "starRating": "TWO",
    "comment": "Acomodándose a nuevos dueños, floja atención y mucha espera\n\n(Translated by Google)\nAdjusting to new owners, poor service and long waits",
    "createTime": "2019-12-25T15:13:18.370217Z",
    "updateTime": "2019-12-25T15:13:18.370217Z",
    "name": "accounts/109853746269412609224/locations/10695122331646821595/reviews/ChZDSUhNMG9nS0VJQ0FnSURNeXN6bFh3EAE"
  }, {
    "reviewer": {
      "displayName": "liliana mendez"
    },
    "starRating": "FOUR",
    "comment": "Cita obligada.\n\n(Translated by Google)\nA must-see.",
    "createTime": "2019-12-24T17:21:40.220130Z",
    "updateTime": "2019-12-24T17:21:40.220130Z",
    "name": "accounts/109853746269412609224/locations/10695122331646821595/reviews/ChdDSUhNMG9nS0VJQ0FnSURNOG9DWjFRRRAB"
  }, {
    "reviewer": {
      "displayName": "Fernando Martín Valsangiacomo"
    },
    "starRating": "FOUR",
    "comment": "(Translated by Google) Everything is fine\n\n(Original)\nВсё хорошо",
    "createTime": "2019-12-24T11:35:39.356427Z",
    "updateTime": "2019-12-24T11:35:39.356427Z",
    "name": "accounts/109853746269412609224/locations/10695122331646821595/reviews/ChdDSUhNMG9nS0VJQ0FnSURNc29USHNnRRAB"
  }, {
    "reviewer": {
      "displayName": "Graciela Buscacci"
    },
    "starRating": "FIVE",
    "comment": "Contento el Rover le llene la panza jaja\n\n(Translated by Google)\nRover was happy to fill his belly haha",
    "createTime": "2019-12-24T09:19:42.670569Z",
    "updateTime": "2019-12-24T09:19:42.670569Z",
    "name": "accounts/109853746269412609224/locations/10695122331646821595/reviews/ChZDSUhNMG9nS0VJQ0FnSURNMHQzNFJREAE"
  }, {
    "reviewer": {
      "displayName": "Edith del valle Guzmán"
    },
    "starRating": "FIVE",
    "comment": "Muy buena la atención\n\n(Translated by Google)\nThe service was very good.",
    "createTime": "2019-12-24T02:42:22.574114Z",
    "updateTime": "2019-12-24T02:42:22.574114Z",
    "name": "accounts/109853746269412609224/locations/10695122331646821595/reviews/ChdDSUhNMG9nS0VJQ0FnSURNMHVDaDdBRRAB"
  }, {
    "reviewer": {
      "displayName": "Gastón Barroso"
    },
    "starRating": "FOUR",
    "createTime": "2019-12-22T02:55:58.754244Z",
    "updateTime": "2019-12-22T02:55:58.754244Z",
    "name": "accounts/109853746269412609224/locations/10695122331646821595/reviews/ChZDSUhNMG9nS0VJQ0FnSURNX04yYWFBEAE"
  }, {
    "reviewer": {
      "displayName": "Javier Cipolatti"
    },
    "starRating": "FOUR",
    "comment": "Buena atención y rapidez\n\n(Translated by Google)\nGood service and fast",
    "createTime": "2019-12-17T14:40:25.914439Z",
    "updateTime": "2019-12-17T14:40:25.914439Z",
    "name": "accounts/109853746269412609224/locations/10695122331646821595/reviews/ChZDSUhNMG9nS0VJQ0FnSURNNU42dk9nEAE"
  }]
}