{
  "reviews": [{
    "reviewer": {
      "displayName": "Liliana Maciel"
    },
    "starRating": "FIVE",
    "comment": "Buena atención,solo los baños bastantes sucios!!\n\n(Translated by Google)\nGood service, just the bathrooms were quite dirty!!",
    "createTime": "2023-01-02T03:03:51.106475Z",
    "updateTime": "2023-01-02T03:03:51.106475Z",
    "name": "accounts/109853746269412609224/locations/5216193713226017652/reviews/ChZDSUhNMG9nS0VJQ0FnSUNCbmNhOEd3EAE"
  }, {
    "reviewer": {
      "displayName": "lorena vazquez barragan"
    },
    "starRating": "ONE",
    "comment": "Baños impresentables , fila para entras , sin papel ni jabón osea lo básico, las puertas no cierran, tachos desbordados y todos sucios\n\n(Translated by Google)\nThe bathrooms are appalling, there\u0027s a line to get in, no toilet paper or soap (the basics), the doors don\u0027t close, the bins are overflowing and filthy.",
    "createTime": "2022-12-30T10:08:57.928036Z",
    "updateTime": "2022-12-30T10:08:57.928036Z",
    "name": "accounts/109853746269412609224/locations/5216193713226017652/reviews/ChdDSUhNMG9nS0VJQ0FnSUNCLWNmUG1nRRAB"
  }, {
    "reviewer": {
      "displayName": "Gustavo"
    },
    "starRating": "FOUR",
    "createTime": "2022-12-28T17:37:30.478128Z",
    "updateTime": "2022-12-28T17:37:30.478128Z",
    "name": "accounts/109853746269412609224/locations/5216193713226017652/reviews/ChZDSUhNMG9nS0VJQ0FnSUNCOFlIRkZBEAE"
  }, {
    "reviewer": {
      "displayName": "A F"
    },
    "starRating": "FOUR",
    "createTime": "2022-12-28T15:03:13.203895Z",
    "updateTime": "2022-12-28T15:03:13.203895Z",
    "name": "accounts/109853746269412609224/locations/5216193713226017652/reviews/ChZDSUhNMG9nS0VJQ0FnSUNCc2ZPbEh3EAE"
  }, {
    "reviewer": {
      "displayName": "Jorge Corrarelle"
    },
    "starRating": "FIVE",
    "createTime": "2022-12-27T20:32:54.526920Z",
    "updateTime": "2022-12-27T20:32:54.526920Z",
    "name": "accounts/109853746269412609224/locations/5216193713226017652/reviews/ChZDSUhNMG9nS0VJQ0FnSUNCNGJqUUNBEAE"
  }, {
    "reviewer": {
      "displayName": "Flavio Julio Catlos Maucci"
    },
    "starRating": "FIVE",
    "comment": "Gente Amable\n\n(Translated by Google)\nFriendly People",
    "createTime": "2022-12-27T00:36:28.380770Z",
    "updateTime": "2022-12-27T00:36:28.380770Z",
    "name": "accounts/109853746269412609224/locations/5216193713226017652/reviews/ChZDSUhNMG9nS0VJQ0FnSUNCdnBhclZREAE"
  }, {
    "reviewer": {
      "displayName": "Jorge Néstor Valle"
    },
    "starRating": "FIVE",
    "comment": "Bien en precios y calidad de YPF muy buena atención. Muy limpio y prolijo\n\n(Translated by Google)\nGood prices and quality at YPF, very good service. Very clean and tidy.",
    "createTime": "2022-12-26T02:03:37.142058Z",
    "updateTime": "2022-12-26T02:03:37.142058Z",
    "name": "accounts/109853746269412609224/locations/5216193713226017652/reviews/ChZDSUhNMG9nS0VJQ0FnSUNCcnNUQlBnEAE"
  }, {
    "reviewer": {
      "displayName": "Roberto Domeniconi"
    },
    "starRating": "FIVE",
    "createTime": "2022-12-26T00:48:28.168572Z",
    "updateTime": "2022-12-26T00:48:28.168572Z",
    "name": "accounts/109853746269412609224/locations/5216193713226017652/reviews/ChZDSUhNMG9nS0VJQ0FnSUNCenJfUVJBEAE"
  }, {
    "reviewer": {
      "displayName": "Ruben Perez"
    },
    "starRating": "THREE",
    "createTime": "2022-12-25T21:49:57.529648Z",
    "updateTime": "2022-12-25T21:49:57.529648Z",
    "name": "accounts/109853746269412609224/locations/5216193713226017652/reviews/ChdDSUhNMG9nS0VJQ0FnSUNCenVYcjR3RRAB"
  }, {
    "reviewer": {
      "displayName": "Fernando Tognis"
    },
    "starRating": "FIVE",
    "comment": "Carga rápida, agua caliente gratis y baños limpios.\n\n(Translated by Google)\nFast charging, free hot water and clean bathrooms.",
    "createTime": "2022-12-25T15:02:23.188598Z",
    "updateTime": "2022-12-25T15:02:23.188598Z",
    "name": "accounts/109853746269412609224/locations/5216193713226017652/reviews/ChdDSUhNMG9nS0VJQ0FnSUNCanFuZW1RRRAB"
  }, {
    "reviewer": {
      "displayName": "d"
    },
    "starRating": "TWO",
    "comment": "No aceptan mercadopago\n\n(Translated by Google)\nThey do not accept Mercado Pago.",
    "createTime": "2022-12-24T19:56:25.792654Z",
    "updateTime": "2022-12-24T19:56:25.792654Z",
    "name": "accounts/109853746269412609224/locations/5216193713226017652/reviews/ChdDSUhNMG9nS0VJQ0FnSUNCMXF2enRBRRAB"
  }, {
    "reviewer": {
      "displayName": "Dr. Salamanca"
    },
    "starRating": "FIVE",
    "comment": "El mejor octanaje. G\n\n(Translated by Google)\nThe best octane. G",
    "createTime": "2022-12-23T17:55:36.841523Z",
    "updateTime": "2022-12-23T17:56:00.193478Z",
    "name": "accounts/109853746269412609224/locations/5216193713226017652/reviews/ChdDSUhNMG9nS0VJQ0FnSUNCeHFURm13RRAB"
  }, {
    "reviewer": {
      "displayName": "Ruben Soria"
    },
    "starRating": "FOUR",
    "comment": "Muy buena atencion tanto por el personal de playa como los que atienden el interior.\nSiempre mantiene una presentación impecable.\n\n(Translated by Google)\nExcellent service from both the beach staff and the indoor staff.\nThey always maintain an impeccable presentation.",
    "createTime": "2022-12-21T02:39:10.880374Z",
    "updateTime": "2022-12-21T02:39:10.880374Z",
    "name": "accounts/109853746269412609224/locations/5216193713226017652/reviews/ChdDSUhNMG9nS0VJQ0FnSUNCNHVPbzJ3RRAB"
  }, {
    "reviewer": {
      "displayName": "Jorge"
    },
    "starRating": "FIVE",
    "comment": "Una estación más del ACA. Buen servicio. Sanitario en buenas condiciones.\n\n(Translated by Google)\nAnother ACA station. Good service. Restroom in good condition.",
    "createTime": "2022-12-20T05:07:17.551954Z",
    "updateTime": "2022-12-20T05:07:17.551954Z",
    "name": "accounts/109853746269412609224/locations/5216193713226017652/reviews/ChdDSUhNMG9nS0VJQ0FnSUNCdk0zWWl3RRAB"
  }, {
    "reviewer": {
      "displayName": "Juan Barge"
    },
    "starRating": "FIVE",
    "comment": "Mi lugar en el mundo\n\n(Translated by Google)\nMy place in the world",
    "createTime": "2022-12-19T20:38:01.763409Z",
    "updateTime": "2022-12-19T20:38:01.763409Z",
    "name": "accounts/109853746269412609224/locations/5216193713226017652/reviews/ChZDSUhNMG9nS0VJQ0FnSUNCM0lxNVJnEAE"
  }, {
    "reviewer": {
      "displayName": "MARIA FAIL"
    },
    "starRating": "FOUR",
    "comment": "hermoso  lugar para descansar con las mascotas\n\n(Translated by Google)\nbeautiful place to rest with pets",
    "createTime": "2022-12-19T19:37:17.436038Z",
    "updateTime": "2022-12-19T19:37:17.436038Z",
    "name": "accounts/109853746269412609224/locations/5216193713226017652/reviews/ChdDSUhNMG9nS0VJQ0FnSUNCM05pdDJRRRAB"
  }, {
    "reviewer": {
      "displayName": "gregorio Uballes"
    },
    "starRating": "THREE",
    "createTime": "2022-12-19T11:38:15.113840Z",
    "updateTime": "2022-12-19T11:38:15.113840Z",
    "name": "accounts/109853746269412609224/locations/5216193713226017652/reviews/ChdDSUhNMG9nS0VJQ0FnSUNCck0tS19nRRAB"
  }, {
    "reviewer": {
      "displayName": "Ariel Noto"
    },
    "starRating": "FIVE",
    "createTime": "2022-12-19T02:50:26.730030Z",
    "updateTime": "2022-12-19T02:50:26.730030Z",
    "name": "accounts/109853746269412609224/locations/5216193713226017652/reviews/ChdDSUhNMG9nS0VJQ0FnSUNCekxLVXVBRRAB"
  }, {
    "reviewer": {
      "displayName": "Andrea Daiana"
    },
    "starRating": "THREE",
    "comment": "Sólo fui al baño.\n\n(Translated by Google)\nI just went to the bathroom.",
    "createTime": "2022-12-18T12:15:28.577728Z",
    "updateTime": "2022-12-18T12:15:28.577728Z",
    "name": "accounts/109853746269412609224/locations/5216193713226017652/reviews/ChZDSUhNMG9nS0VJQ0FnSUNCdEpiQ0tREAE"
  }, {
    "reviewer": {
      "displayName": "Carlos Miguez"
    },
    "starRating": "THREE",
    "createTime": "2022-12-18T02:26:47.482184Z",
    "updateTime": "2022-12-18T02:26:47.482184Z",
    "name": "accounts/109853746269412609224/locations/5216193713226017652/reviews/ChZDSUhNMG9nS0VJQ0FnSUNCbElYdVRnEAE"
  }]
}