{
  "reviews": [{
    "reviewer": {
      "displayName": "Gabyferchu_2011@hotmail.com Fernandez"
    },
    "starRating": "THREE",
    "createTime": "2017-11-21T14:22:37.462Z",
    "updateTime": "2017-11-21T14:22:37.462Z",
    "name": "accounts/109853746269412609224/locations/14276783751635166039/reviews/ChdDSUhNMG9nS0VJQ0FnSURBLXFTMy1BRRAB"
  }, {
    "reviewer": {
      "displayName": "Maria Alejandra Garcia"
    },
    "starRating": "FIVE",
    "comment": "Calculo las paradas para incluir este sitio en mi carga de combustible. Al entrar o salir de la ruta al desierto, es el mejor lugar para parar y descansar, está al costado de la ruta, y al lado del río. Tiene un shop completo, baños impecables, atención amable, lindo lugar, buen combustible.\n\n(Translated by Google)\nI plan my stops to include this place in my fuel schedule. When entering or leaving the desert route, it\u0027s the best place to stop and rest. It\u0027s right off the road and next to the river. It has a full shop, spotless restrooms, friendly service, a nice atmosphere, and good fuel.",
    "createTime": "2017-11-21T11:01:34.733Z",
    "updateTime": "2017-11-21T11:01:34.733Z",
    "reviewReply": {
      "comment": "Gracias por su comentario María ",
      "updateTime": "2025-07-19T20:31:11.872358Z"
    },
    "name": "accounts/109853746269412609224/locations/14276783751635166039/reviews/ChZDSUhNMG9nS0VJQ0FnSUN3cDU3aGJBEAE"
  }, {
    "reviewer": {
      "displayName": "Paolo Sartor"
    },
    "starRating": "FOUR",
    "createTime": "2017-11-21T01:19:12.359Z",
    "updateTime": "2017-11-21T01:19:12.359Z",
    "name": "accounts/109853746269412609224/locations/14276783751635166039/reviews/ChZDSUhNMG9nS0VJQ0FnSURBdWYyU0RnEAE"
  }, {
    "reviewer": {
      "displayName": "Carlos Arrieta"
    },
    "starRating": "THREE",
    "createTime": "2017-11-20T23:08:54.716Z",
    "updateTime": "2017-11-20T23:08:54.716Z",
    "name": "accounts/109853746269412609224/locations/14276783751635166039/reviews/ChdDSUhNMG9nS0VJQ0FnSURBaE42Snl3RRAB"
  }, {
    "reviewer": {
      "displayName": "Claudio Cherry"
    },
    "starRating": "THREE",
    "comment": "No destaca de otras Estaciones de servicios\n\n(Translated by Google)\nIt doesn\u0027t stand out from other service stations",
    "createTime": "2017-11-20T00:59:00.867Z",
    "updateTime": "2017-11-20T00:59:22.993Z",
    "name": "accounts/109853746269412609224/locations/14276783751635166039/reviews/ChZDSUhNMG9nS0VJQ0FnSUNnanNYbEhnEAE"
  }, {
    "reviewer": {
      "displayName": "Nestor Di Franco"
    },
    "starRating": "THREE",
    "createTime": "2017-11-19T12:30:16.558Z",
    "updateTime": "2017-11-19T12:30:16.558Z",
    "name": "accounts/109853746269412609224/locations/14276783751635166039/reviews/ChdDSUhNMG9nS0VJQ0FnSUNRM2FfanJBRRAB"
  }, {
    "reviewer": {
      "displayName": "Carlos Rios"
    },
    "starRating": "FIVE",
    "comment": "Muy buena atención!\n\n(Translated by Google)\nExcellent service!",
    "createTime": "2017-11-18T21:04:12.095Z",
    "updateTime": "2017-11-18T21:04:24.937Z",
    "name": "accounts/109853746269412609224/locations/14276783751635166039/reviews/ChdDSUhNMG9nS0VJQ0FnSURnNl9faXBnRRAB"
  }, {
    "reviewer": {
      "displayName": "Rubén Navarro"
    },
    "starRating": "THREE",
    "comment": "Buen servicio.\n\n(Translated by Google)\nGood service.",
    "createTime": "2017-11-18T18:16:50.768Z",
    "updateTime": "2017-11-18T18:17:13.830Z",
    "name": "accounts/109853746269412609224/locations/14276783751635166039/reviews/ChdDSUhNMG9nS0VJQ0FnSUNRcDVPYnhBRRAB"
  }, {
    "reviewer": {
      "displayName": "Eduardo Angelo"
    },
    "starRating": "FOUR",
    "createTime": "2017-11-18T18:04:41.637Z",
    "updateTime": "2017-11-18T18:04:41.637Z",
    "name": "accounts/109853746269412609224/locations/14276783751635166039/reviews/ChZDSUhNMG9nS0VJQ0FnSUNBaC1qVllREAE"
  }, {
    "reviewer": {
      "displayName": "SERGIO RAUL VIOLA"
    },
    "starRating": "THREE",
    "comment": "Mucha espera, y muy caros los precios del servicompras\n\n(Translated by Google)\nLong wait, and very expensive prices for servicompras",
    "createTime": "2017-11-18T11:33:27.929Z",
    "updateTime": "2017-11-18T11:33:56.897Z",
    "name": "accounts/109853746269412609224/locations/14276783751635166039/reviews/ChZDSUhNMG9nS0VJQ0FnSUNRaHVLR1lREAE"
  }, {
    "reviewer": {
      "displayName": "Daniel Campo"
    },
    "starRating": "FOUR",
    "comment": "Muy buen servicio.\n\n(Translated by Google)\nVery good service.",
    "createTime": "2017-11-18T10:52:42.513Z",
    "updateTime": "2017-11-18T10:52:54.223Z",
    "name": "accounts/109853746269412609224/locations/14276783751635166039/reviews/ChZDSUhNMG9nS0VJQ0FnSUNRdXZEU0dREAE"
  }, {
    "reviewer": {
      "displayName": "GUSTAVO WALTER SCHVIND"
    },
    "starRating": "FIVE",
    "comment": "Bien\n\n(Translated by Google)\nGood",
    "createTime": "2017-11-18T02:56:23.815Z",
    "updateTime": "2017-11-18T02:56:29.862Z",
    "name": "accounts/109853746269412609224/locations/14276783751635166039/reviews/ChZDSUhNMG9nS0VJQ0FnSUNBcnNPZUtREAE"
  }, {
    "reviewer": {
      "displayName": "Marcelo Bianchi"
    },
    "starRating": "FOUR",
    "comment": "Todo bien\n\n(Translated by Google)\nAll good",
    "createTime": "2017-11-18T01:01:42.550Z",
    "updateTime": "2017-11-18T01:01:51.376Z",
    "name": "accounts/109853746269412609224/locations/14276783751635166039/reviews/ChZDSUhNMG9nS0VJQ0FnSUN3dDk3TmFnEAE"
  }, {
    "reviewer": {
      "displayName": "Guillermo Claudio Forcinito"
    },
    "starRating": "THREE",
    "comment": "Buena atención del personal, aunque suele ser lenta la carga\n\n(Translated by Google)\nThe staff were helpful, although loading can be slow.",
    "createTime": "2017-11-17T00:06:09.778Z",
    "updateTime": "2017-11-17T00:07:53.709Z",
    "name": "accounts/109853746269412609224/locations/14276783751635166039/reviews/ChZDSUhNMG9nS0VJQ0FnSUN3bzUtSEJBEAE"
  }, {
    "reviewer": {
      "displayName": "Mara Brizuela"
    },
    "starRating": "FIVE",
    "comment": "Buena atención\n\n(Translated by Google)\nGood service",
    "createTime": "2017-11-16T23:57:32.314Z",
    "updateTime": "2017-11-16T23:57:40.993Z",
    "name": "accounts/109853746269412609224/locations/14276783751635166039/reviews/ChZDSUhNMG9nS0VJQ0FnSUNRbHYta1pREAE"
  }, {
    "reviewer": {
      "displayName": "Gaston Torrico"
    },
    "starRating": "FOUR",
    "createTime": "2017-11-16T14:34:45.737Z",
    "updateTime": "2017-11-16T14:34:45.737Z",
    "name": "accounts/109853746269412609224/locations/14276783751635166039/reviews/ChdDSUhNMG9nS0VJQ0FnSURBdElqbG1nRRAB"
  }, {
    "reviewer": {
      "displayName": "Veronica Villalba"
    },
    "starRating": "THREE",
    "createTime": "2017-11-15T21:40:18.573Z",
    "updateTime": "2017-11-15T21:40:18.573Z",
    "name": "accounts/109853746269412609224/locations/14276783751635166039/reviews/ChZDSUhNMG9nS0VJQ0FnSURnMjcyU1ZBEAE"
  }, {
    "reviewer": {
      "displayName": "Gabriela Bercovich"
    },
    "starRating": "ONE",
    "comment": "No dan factura muy mala la atención. Tampoco tienen débito\n\n(Translated by Google)\nThey don\u0027t provide receipts, the service is very bad. They also don\u0027t accept debit cards.",
    "createTime": "2017-11-15T21:33:18.921Z",
    "updateTime": "2017-11-15T21:33:50.110Z",
    "name": "accounts/109853746269412609224/locations/14276783751635166039/reviews/ChZDSUhNMG9nS0VJQ0FnSURBc1kybWVnEAE"
  }, {
    "reviewer": {
      "displayName": "Martin Giozue"
    },
    "starRating": "FIVE",
    "comment": "Mut buen servicio\n\n(Translated by Google)\nVery good service",
    "createTime": "2017-11-15T18:35:45.179Z",
    "updateTime": "2017-11-15T18:36:27.820Z",
    "name": "accounts/109853746269412609224/locations/14276783751635166039/reviews/ChdDSUhNMG9nS0VJQ0FnSUNnM2V5UG53RRAB"
  }, {
    "reviewer": {
      "displayName": "Florencio Diaz"
    },
    "starRating": "FOUR",
    "comment": "Buena atención\n\n(Translated by Google)\nGood service",
    "createTime": "2017-11-12T14:06:37.833Z",
    "updateTime": "2017-11-12T14:06:50.159Z",
    "name": "accounts/109853746269412609224/locations/14276783751635166039/reviews/ChZDSUhNMG9nS0VJQ0FnSUN3bzQyLUd3EAE"
  }]
}