{
  "reviews": [{
    "reviewer": {
      "displayName": "Leo Minet"
    },
    "starRating": "FIVE",
    "comment": "Calidad en el centro de San Juan\n\n(Translated by Google)\nQuality in the heart of San Juan",
    "createTime": "2023-06-26T12:45:20.067778Z",
    "updateTime": "2023-06-26T12:45:20.067778Z",
    "name": "accounts/109853746269412609224/locations/11544579934196333833/reviews/ChdDSUhNMG9nS0VJQ0FnSUNKNXJhNTJnRRAB"
  }, {
    "reviewer": {
      "displayName": "C. Cecche"
    },
    "starRating": "FIVE",
    "comment": "Excelente estación de servicio\n\n(Translated by Google)\nExcellent gas station",
    "createTime": "2023-06-23T12:47:55.484308Z",
    "updateTime": "2023-06-23T12:47:55.484308Z",
    "name": "accounts/109853746269412609224/locations/11544579934196333833/reviews/ChdDSUhNMG9nS0VJQ0FnSUNKZ3FlVzZ3RRAB"
  }, {
    "reviewer": {
      "displayName": "Polo Dicarlo"
    },
    "starRating": "THREE",
    "comment": "Un poco demoroso.\n\n(Translated by Google)\nA little slow.",
    "createTime": "2023-06-15T02:27:35.990590Z",
    "updateTime": "2023-06-15T02:27:35.990590Z",
    "name": "accounts/109853746269412609224/locations/11544579934196333833/reviews/ChZDSUhNMG9nS0VJQ0FnSUR4eTRhbVhnEAE"
  }, {
    "reviewer": {
      "displayName": "Luis Melicchio"
    },
    "starRating": "FIVE",
    "comment": "Excelente atención.\n\n(Translated by Google)\nExcellent service.",
    "createTime": "2023-06-12T01:39:03.250266Z",
    "updateTime": "2023-06-12T01:39:03.250266Z",
    "name": "accounts/109853746269412609224/locations/11544579934196333833/reviews/ChZDSUhNMG9nS0VJQ0FnSUR4aFl1TFJBEAE"
  }, {
    "reviewer": {
      "displayName": "Rodolfo Alvarez Oro"
    },
    "starRating": "TWO",
    "comment": "Falta de personal\n\n(Translated by Google)\nStaff shortage",
    "createTime": "2023-06-09T15:32:24.208430Z",
    "updateTime": "2023-06-09T15:32:24.208430Z",
    "name": "accounts/109853746269412609224/locations/11544579934196333833/reviews/ChdDSUhNMG9nS0VJQ0FnSUR4d2U2V2xnRRAB"
  }, {
    "reviewer": {
      "displayName": "A F"
    },
    "starRating": "ONE",
    "comment": "Un desastre, reserve un turno con YPF box a las 6:00 de la mañana, y nunca me atendieron. Estuve 50 minutos esperando, me dijeron que \"no encontraban las llaves\". A nadie le importaba que se perdiera un cliente, todos encerrados para no tomar frío. Nunca más!\n\n(Translated by Google)\nA disaster! I booked an appointment at the YPF service station at 6:00 AM, and they never attended to me. I waited 50 minutes, and they told me they \"couldn\u0027t find the keys.\" Nobody cared that a customer was being lost; everyone was locked inside to avoid the cold. Never again!",
    "createTime": "2023-06-06T10:11:11.526310Z",
    "updateTime": "2023-06-06T10:11:11.526310Z",
    "name": "accounts/109853746269412609224/locations/11544579934196333833/reviews/ChdDSUhNMG9nS0VJQ0FnSUR4bXJLYzVnRRAB"
  }, {
    "reviewer": {
      "displayName": "Alfonso Chaves Huertas"
    },
    "starRating": "ONE",
    "createTime": "2023-06-03T16:11:36.192124Z",
    "updateTime": "2023-06-03T16:11:45.470693Z",
    "name": "accounts/109853746269412609224/locations/11544579934196333833/reviews/ChZDSUhNMG9nS0VJQ0FnSUR4N0t1M2VBEAE"
  }, {
    "reviewer": {
      "displayName": "Marcelo Fernandez"
    },
    "starRating": "THREE",
    "createTime": "2023-06-02T23:48:37.434656Z",
    "updateTime": "2023-06-02T23:48:37.434656Z",
    "name": "accounts/109853746269412609224/locations/11544579934196333833/reviews/ChdDSUhNMG9nS0VJQ0FnSUR4OUwzSjVnRRAB"
  }, {
    "reviewer": {
      "displayName": "jose luis pesamosca"
    },
    "starRating": "FIVE",
    "createTime": "2023-05-26T11:37:39.938608Z",
    "updateTime": "2023-05-26T11:37:57.465835Z",
    "name": "accounts/109853746269412609224/locations/11544579934196333833/reviews/ChdDSUhNMG9nS0VJQ0FnSUN4cTZmanhBRRAB"
  }, {
    "reviewer": {
      "displayName": "carlos arturo Genesoni"
    },
    "starRating": "THREE",
    "createTime": "2023-05-24T16:37:03.650537Z",
    "updateTime": "2023-05-24T16:37:03.650537Z",
    "name": "accounts/109853746269412609224/locations/11544579934196333833/reviews/ChZDSUhNMG9nS0VJQ0FnSUN4dzhyUGFREAE"
  }, {
    "reviewer": {
      "displayName": "Gabriela Valenzuela"
    },
    "starRating": "FIVE",
    "comment": "La mejor YPF lejos. La atención es de otro nivel.\n\n(Translated by Google)\nThe best YPF by far. The service is on another level.",
    "createTime": "2023-05-23T11:15:50.197936Z",
    "updateTime": "2023-05-23T11:15:50.197936Z",
    "name": "accounts/109853746269412609224/locations/11544579934196333833/reviews/ChZDSUhNMG9nS0VJQ0FnSUN4elpQS2RBEAE"
  }, {
    "reviewer": {
      "displayName": "Ricardo M. MORALES"
    },
    "starRating": "THREE",
    "comment": "Buena atención y organizacion, incluso estando con refacciones. Sigue sin funcionar el equipo de revisión e inflado de ruedas\n\n(Translated by Google)\nGood service and organization, even with spare parts. The tire inspection and inflation equipment is still not working.",
    "createTime": "2023-05-17T19:24:44.566003Z",
    "updateTime": "2023-05-17T19:24:44.566003Z",
    "name": "accounts/109853746269412609224/locations/11544579934196333833/reviews/ChdDSUhNMG9nS0VJQ0FnSUN4cnNDLS1RRRAB"
  }, {
    "reviewer": {
      "displayName": "Ethel Respecte"
    },
    "starRating": "FIVE",
    "createTime": "2023-05-16T14:49:31.606582Z",
    "updateTime": "2023-05-16T14:49:31.606582Z",
    "name": "accounts/109853746269412609224/locations/11544579934196333833/reviews/ChZDSUhNMG9nS0VJQ0FnSUN4cHRMbVRnEAE"
  }, {
    "reviewer": {
      "displayName": "Silvana Rouco Oliva"
    },
    "starRating": "FIVE",
    "createTime": "2023-05-07T22:53:18.520025Z",
    "updateTime": "2023-05-07T22:53:18.520025Z",
    "name": "accounts/109853746269412609224/locations/11544579934196333833/reviews/ChdDSUhNMG9nS0VJQ0FnSUN4Z05Yemx3RRAB"
  }, {
    "reviewer": {
      "displayName": "juan pablo conti"
    },
    "starRating": "FIVE",
    "createTime": "2023-05-07T04:14:55.101590Z",
    "updateTime": "2023-05-07T04:14:55.101590Z",
    "name": "accounts/109853746269412609224/locations/11544579934196333833/reviews/ChZDSUhNMG9nS0VJQ0FnSURSbjZqZGFREAE"
  }, {
    "reviewer": {
      "displayName": "Elizz soñadora"
    },
    "starRating": "FIVE",
    "comment": "Si no se pasas por hay no se siguen\n\n(Translated by Google)\nIf you don\u0027t go there, you won\u0027t continue.",
    "createTime": "2023-05-02T04:33:53.014748Z",
    "updateTime": "2023-05-07T00:30:43.286602Z",
    "name": "accounts/109853746269412609224/locations/11544579934196333833/reviews/ChZDSUhNMG9nS0VJQ0FnSURSdmJfT0tREAE"
  }, {
    "reviewer": {
      "displayName": "Sergio Rivero"
    },
    "starRating": "FIVE",
    "comment": "Buena atención de sus playeros. Facilidades con las opciones d pago.\n\n(Translated by Google)\nExcellent service from the beach attendants. Convenient payment options.",
    "createTime": "2023-04-25T15:36:16.425891Z",
    "updateTime": "2023-04-25T15:36:16.425891Z",
    "name": "accounts/109853746269412609224/locations/11544579934196333833/reviews/ChdDSUhNMG9nS0VJQ0FnSURScnQ3NjRnRRAB"
  }, {
    "reviewer": {
      "displayName": "franco llull"
    },
    "starRating": "FOUR",
    "comment": "Buena estación de servicio.un poco lento en hora pico la atención. Pero bien.\n\n(Translated by Google)\nGood gas station. Service is a bit slow during peak hours. But it\u0027s okay.",
    "createTime": "2023-04-21T22:31:06.868648Z",
    "updateTime": "2023-04-21T22:31:06.868648Z",
    "name": "accounts/109853746269412609224/locations/11544579934196333833/reviews/ChZDSUhNMG9nS0VJQ0FnSURSc3U3c2J3EAE"
  }, {
    "reviewer": {
      "displayName": "RODO2447"
    },
    "starRating": "FIVE",
    "comment": "Rápida atención en la carga de combustible y venta de sus productos lubricantes y de limpieza. La atención de su personal es respetuosa y muy cordial\n\n(Translated by Google)\nFast service for fueling and sales of their lubricants and cleaning products. Their staff is respectful and very friendly.",
    "createTime": "2023-04-12T18:30:04.386502Z",
    "updateTime": "2023-04-12T18:30:04.386502Z",
    "name": "accounts/109853746269412609224/locations/11544579934196333833/reviews/ChdDSUhNMG9nS0VJQ0FnSUNSMV9xN3lRRRAB"
  }, {
    "reviewer": {
      "displayName": "Gabriela Tello"
    },
    "starRating": "FIVE",
    "createTime": "2023-04-05T18:27:08.904209Z",
    "updateTime": "2023-04-05T18:27:08.904209Z",
    "name": "accounts/109853746269412609224/locations/11544579934196333833/reviews/ChdDSUhNMG9nS0VJQ0FnSUNSMmYyejJRRRAB"
  }]
}