{
  "reviews": [{
    "reviewer": {
      "displayName": "Gonzalo Espíndola"
    },
    "starRating": "FOUR",
    "createTime": "2017-02-16T01:30:35.053Z",
    "updateTime": "2017-02-16T01:30:35.053Z",
    "name": "accounts/109853746269412609224/locations/8171823765692458471/reviews/ChdDSUhNMG9nS0VJQ0FnSURnd0liUy1BRRAB"
  }, {
    "reviewer": {
      "displayName": "Angel Fabio Guillelmi"
    },
    "starRating": "FIVE",
    "createTime": "2017-02-10T17:54:41.449Z",
    "updateTime": "2017-02-10T17:54:41.449Z",
    "name": "accounts/109853746269412609224/locations/8171823765692458471/reviews/ChZDSUhNMG9nS0VJQ0FnSURBc2JiVUN3EAE"
  }, {
    "reviewer": {
      "displayName": "Héctor moderell"
    },
    "starRating": "FIVE",
    "createTime": "2017-02-10T12:54:41.310Z",
    "updateTime": "2017-02-10T12:54:41.310Z",
    "name": "accounts/109853746269412609224/locations/8171823765692458471/reviews/ChZDSUhNMG9nS0VJQ0FnSUNBMF9HSFFnEAE"
  }, {
    "reviewer": {
      "displayName": "sergio marquez"
    },
    "starRating": "FOUR",
    "createTime": "2017-01-29T23:33:50.060Z",
    "updateTime": "2017-01-29T23:33:50.060Z",
    "name": "accounts/109853746269412609224/locations/8171823765692458471/reviews/ChdDSUhNMG9nS0VJQ0FnSURRN0xxUW1BRRAB"
  }, {
    "reviewer": {
      "displayName": "Enrique Schvartz"
    },
    "starRating": "THREE",
    "createTime": "2017-01-26T10:10:04.792Z",
    "updateTime": "2017-01-26T10:10:04.792Z",
    "name": "accounts/109853746269412609224/locations/8171823765692458471/reviews/ChdDSUhNMG9nS0VJQ0FnSURneUszZXRRRRAB"
  }, {
    "reviewer": {
      "displayName": "Fernando Cornejo Valdivia"
    },
    "starRating": "FIVE",
    "comment": "Siempre hay un buen servicio\n\n(Translated by Google)\nThere is always good service.",
    "createTime": "2017-01-23T03:35:54.548Z",
    "updateTime": "2017-01-24T17:44:15.613Z",
    "name": "accounts/109853746269412609224/locations/8171823765692458471/reviews/ChZDSUhNMG9nS0VJQ0FnSURBaF9pVWVnEAE"
  }, {
    "reviewer": {
      "displayName": "Ramón Llanos"
    },
    "starRating": "FIVE",
    "comment": "Lugar de paso para cargar combustible, saliendo hacia el norte\n\n(Translated by Google)\nStop for refueling, heading north",
    "createTime": "2017-01-22T15:05:50.837Z",
    "updateTime": "2017-01-22T15:06:46.254Z",
    "name": "accounts/109853746269412609224/locations/8171823765692458471/reviews/ChdDSUhNMG9nS0VJQ0FnSURnMzVHNjdRRRAB"
  }, {
    "reviewer": {
      "displayName": "Sergio Bruno"
    },
    "starRating": "THREE",
    "createTime": "2017-01-13T21:03:04.007Z",
    "updateTime": "2017-01-13T21:03:04.007Z",
    "name": "accounts/109853746269412609224/locations/8171823765692458471/reviews/ChdDSUhNMG9nS0VJQ0FnSURnLTdTa3BnRRAB"
  }, {
    "reviewer": {
      "displayName": "Miguel Garcia"
    },
    "starRating": "FIVE",
    "comment": "Rápido y seguro\n\n(Translated by Google)\nFast and safe",
    "createTime": "2017-01-04T15:08:03.527Z",
    "updateTime": "2017-01-04T15:08:09.262Z",
    "name": "accounts/109853746269412609224/locations/8171823765692458471/reviews/ChZDSUhNMG9nS0VJQ0FnSUNROE9US0JnEAE"
  }, {
    "reviewer": {
      "displayName": "Benja Paz"
    },
    "starRating": "THREE",
    "createTime": "2017-01-02T12:56:26.420Z",
    "updateTime": "2017-01-02T12:56:26.420Z",
    "name": "accounts/109853746269412609224/locations/8171823765692458471/reviews/ChdDSUhNMG9nS0VJQ0FnSUNnbWVLaDl3RRAB"
  }, {
    "reviewer": {
      "displayName": "Roberto Amado"
    },
    "starRating": "FOUR",
    "comment": "(Translated by Google) And\n\n(Original)\nSi",
    "createTime": "2016-12-25T13:11:20.269Z",
    "updateTime": "2016-12-25T13:11:36.014Z",
    "name": "accounts/109853746269412609224/locations/8171823765692458471/reviews/ChZDSUhNMG9nS0VJQ0FnSURBOHVlRVFREAE"
  }, {
    "reviewer": {
      "displayName": "Eduardo Matías Moreno"
    },
    "starRating": "FIVE",
    "createTime": "2016-12-21T14:31:15.444Z",
    "updateTime": "2016-12-21T14:31:15.444Z",
    "name": "accounts/109853746269412609224/locations/8171823765692458471/reviews/ChdDSUhNMG9nS0VJQ0FnSUN3MU9HRzFRRRAB"
  }, {
    "reviewer": {
      "displayName": "Federico"
    },
    "starRating": "FOUR",
    "comment": "Muy buena atención.\n\n(Translated by Google)\nExcellent service.",
    "createTime": "2016-12-14T15:19:54.289Z",
    "updateTime": "2016-12-14T15:20:04.767Z",
    "name": "accounts/109853746269412609224/locations/8171823765692458471/reviews/ChZDSUhNMG9nS0VJQ0FnSURnOXJHRElnEAE"
  }, {
    "reviewer": {
      "displayName": "Tony Tejada"
    },
    "starRating": "THREE",
    "comment": "Es un lugar pequeño; aceptable para el que va de tránsito y necesario\n\n(Translated by Google)\nIt\u0027s a small place; acceptable for those passing through and necessary.",
    "createTime": "2016-12-14T12:13:44.694Z",
    "updateTime": "2016-12-14T12:14:47.054Z",
    "name": "accounts/109853746269412609224/locations/8171823765692458471/reviews/ChdDSUhNMG9nS0VJQ0FnSUNBdWZxRHVBRRAB"
  }, {
    "reviewer": {
      "displayName": "Leandro Rojano"
    },
    "starRating": "FIVE",
    "comment": "Excelente servicio\n\n(Translated by Google)\nExcellent service",
    "createTime": "2016-12-11T16:30:36.896Z",
    "updateTime": "2016-12-11T16:30:49.523Z",
    "name": "accounts/109853746269412609224/locations/8171823765692458471/reviews/ChdDSUhNMG9nS0VJQ0FnSUN3dzdtNC1nRRAB"
  }, {
    "reviewer": {
      "displayName": "Luisa María Méndez"
    },
    "starRating": "FIVE",
    "createTime": "2016-12-09T18:02:54.279Z",
    "updateTime": "2016-12-09T18:02:54.279Z",
    "name": "accounts/109853746269412609224/locations/8171823765692458471/reviews/ChdDSUhNMG9nS0VJQ0FnSUNBM1AydTlRRRAB"
  }, {
    "reviewer": {
      "displayName": "Pablo Antonio Garcia"
    },
    "starRating": "FOUR",
    "comment": "Buena atención. Siempre reciben débito y crédito.\n\n(Translated by Google)\nGood service. They always accept debit and credit cards.",
    "createTime": "2016-11-09T09:57:22.565Z",
    "updateTime": "2016-11-16T23:23:13.034Z",
    "name": "accounts/109853746269412609224/locations/8171823765692458471/reviews/ChdDSUhNMG9nS0VJQ0FnSURnMy1qSWp3RRAB"
  }, {
    "reviewer": {
      "displayName": "Jose Alberto Villoria"
    },
    "starRating": "THREE",
    "comment": "Es buena , tiene demasiada señalización q ya llega a estorbar el paso de los vehículos tiene q sacar\n\n(Translated by Google)\nIt\u0027s good, but it has too much signage that it\u0027s starting to obstruct the passage of vehicles; they need to remove it.",
    "createTime": "2016-10-25T09:19:22.866Z",
    "updateTime": "2016-10-25T09:20:35.992Z",
    "name": "accounts/109853746269412609224/locations/8171823765692458471/reviews/ChZDSUhNMG9nS0VJQ0FnSURnOFBlUk9REAE"
  }, {
    "reviewer": {
      "displayName": "Fabricio Costanzo"
    },
    "starRating": "FIVE",
    "createTime": "2016-10-08T13:49:45.391Z",
    "updateTime": "2016-10-08T13:49:45.391Z",
    "name": "accounts/109853746269412609224/locations/8171823765692458471/reviews/ChdDSUhNMG9nS0VJQ0FnSURRMUppcWx3RRAB"
  }, {
    "reviewer": {
      "displayName": "Rodrii Soclly"
    },
    "starRating": "FIVE",
    "createTime": "2016-08-20T18:22:27.162Z",
    "updateTime": "2016-08-20T18:22:27.162Z",
    "name": "accounts/109853746269412609224/locations/8171823765692458471/reviews/ChZDSUhNMG9nS0VJQ0FnSUNBbExma2ZnEAE"
  }]
}