{
  "reviews": [{
    "reviewer": {
      "displayName": "Nora Scherva"
    },
    "starRating": "FIVE",
    "comment": "Muy buena la atención De los empleados de playa\n\n(Translated by Google)\nThe service from the beach staff was excellent.",
    "createTime": "2026-01-09T16:32:48.502863Z",
    "updateTime": "2026-01-09T16:34:45.117267Z",
    "reviewReply": {
      "comment": "Hola Nora! Muchas gracias por tu comentario!!  Te esperamos de vuelta pronto!! ",
      "updateTime": "2026-01-09T18:59:46.459152Z"
    },
    "name": "accounts/109853746269412609224/locations/5256422588388150484/reviews/Ci9DQUlRQUNvZENodHljRjlvT25kVmMzTkpaalJ0T0dkRVNrVkNaRUZSVEdSdVdXYxAB"
  }, {
    "reviewer": {
      "displayName": "Guido Travi"
    },
    "starRating": "FIVE",
    "comment": "Excelente servicio, mención especial a los chicos de la playa que siempre tienen la mejor predisposición para todo lo que se le pide.\n\n(Translated by Google)\nExcellent service, special mention to the beach staff who are always very helpful and willing to assist with anything asked of them.",
    "createTime": "2026-01-09T16:20:27.397853Z",
    "updateTime": "2026-01-09T16:20:27.397853Z",
    "reviewReply": {
      "comment": "Hola Adriana! Muchas gracias por tu comentario!!!  Te esperamos de vuelta pronto!! ",
      "updateTime": "2026-01-09T19:00:25.811271Z"
    },
    "name": "accounts/109853746269412609224/locations/5256422588388150484/reviews/Ci9DQUlRQUNvZENodHljRjlvT25KSk9TMUdNMVpoT0ZJeGJVTk9SRUYyVFdaUlVYYxAB"
  }, {
    "reviewer": {
      "displayName": "Alfredo Fermoselle"
    },
    "starRating": "THREE",
    "comment": "Como estacion d servicio, taller etc bien ahora el lavadero deja mucho q desear, soy socio del aca pague x un servicio completo y termine pidiendole el trapo para limpiar los socalos y paragolpes xq hacia d cuenta q estaba en el barro, se culpan unos a otros, lo unico q t dicen haga el reclamo y q le den un lavado gratis, no es asi el lavado debe d ser como corresponde\n\n(Translated by Google)\nAs a service station, workshop, etc., it\u0027s fine, but the car wash leaves much to be desired. I\u0027m a member, I paid for a full service, and I ended up asking for a rag to clean the rocker panels and bumpers because it was like I was driving through mud. They blame each other; the only thing they tell you is to file a complaint and get a free wash. That\u0027s not how it works; the car wash should be done properly.",
    "createTime": "2026-01-09T14:49:02.800663Z",
    "updateTime": "2026-01-09T14:58:49.280537Z",
    "reviewReply": {
      "comment": "Hola Alfredo, ante todo le pedimos disculpas por lo ocurrido.  Tal como menciona, lo importante es que el vehículo salga en excelentes condiciones en todos los lavados!  Nos ayudaría mucho si pudiera mencionarnos algún dato más preciso como día y horario en que nos visitó para poder evaluar y trabajar con el personal.  Si quiere puede contactarnos por privado y seguimos tratando su reclamo.  Desde ya muchas gracias por su tiempo!!  ",
      "updateTime": "2026-01-09T19:04:58.578521Z"
    },
    "name": "accounts/109853746269412609224/locations/5256422588388150484/reviews/Ci9DQUlRQUNvZENodHljRjlvT21aMGFHSnFTM2MxYlRZdE9FMTRUbG80TWtGb09VRRAB"
  }, {
    "reviewer": {
      "displayName": "Paula Pockay"
    },
    "starRating": "FIVE",
    "comment": "Excelente atención y servicio en Boxes!\n\n(Translated by Google)\nExcellent attention and service in the pits!",
    "createTime": "2026-01-09T14:31:23.364166Z",
    "updateTime": "2026-01-09T14:31:23.364166Z",
    "reviewReply": {
      "comment": "Hola Paula! Muchas gracias por tu comentario!! Te esperamos de vuelta pronto!!",
      "updateTime": "2026-01-09T19:05:29.790148Z"
    },
    "name": "accounts/109853746269412609224/locations/5256422588388150484/reviews/Ci9DQUlRQUNvZENodHljRjlvT2xCWFprTm9WV2wyVWpOSFNuSlhhbGx4U0VGVGNGRRAB"
  }, {
    "reviewer": {
      "displayName": "Javier J. Santiago B"
    },
    "starRating": "FIVE",
    "comment": "Excelente atención por los chicos de los Boxes.\n\n(Translated by Google)\nExcellent service from the guys at the pits.",
    "createTime": "2026-01-09T14:19:59.548030Z",
    "updateTime": "2026-01-09T14:19:59.548030Z",
    "reviewReply": {
      "comment": "Hola Javier! Muchas gracias por tu comentario!! Te esperamos de vuelta pronto!!",
      "updateTime": "2026-01-09T19:05:47.176919Z"
    },
    "name": "accounts/109853746269412609224/locations/5256422588388150484/reviews/Ci9DQUlRQUNvZENodHljRjlvT2xad09YUk1YMHRQVWxCQ1VYTm5lazVRUmtFd2ExRRAB"
  }, {
    "reviewer": {
      "displayName": "Julián B"
    },
    "starRating": "FIVE",
    "createTime": "2019-06-09T15:39:06.243883Z",
    "updateTime": "2026-01-09T04:26:07.732313Z",
    "reviewReply": {
      "comment": "Hola Julián!  Muchas gracias por calificarnos!!",
      "updateTime": "2026-01-09T19:07:53.671899Z"
    },
    "name": "accounts/109853746269412609224/locations/5256422588388150484/reviews/ChdDSUhNMG9nS0VJQ0FnSUM0bWVfN213RRAB"
  }, {
    "reviewer": {
      "displayName": "Sergio Luis Garcia"
    },
    "starRating": "THREE",
    "comment": "Te atienden como a desgano pero pasable\n\n(Translated by Google)\nThey serve you reluctantly, but it\u0027s acceptable.",
    "createTime": "2026-01-08T21:38:18.563238Z",
    "updateTime": "2026-01-08T21:38:18.563238Z",
    "reviewReply": {
      "comment": "Hola Sergio, gracias por comentarnos!  Nos ayudaría mucho si nos comenta también algunos datos mas respecto al momento de su visita para trabajar con el personal, como por ejemplo que día concurrió, en que horario, o si recuerda quién lo ha atendido.  Desde ya muchas gracias!!",
      "updateTime": "2026-01-09T18:57:40.376650Z"
    },
    "name": "accounts/109853746269412609224/locations/5256422588388150484/reviews/Ci9DQUlRQUNvZENodHljRjlvT25Fd1lYRkxjRGxQTUhJdFdFNVBNbUZDVW5wZlZIYxAB"
  }, {
    "reviewer": {
      "displayName": "Decolightvm by Fatima"
    },
    "starRating": "FIVE",
    "createTime": "2026-01-07T23:08:24.941505Z",
    "updateTime": "2026-01-07T23:08:24.941505Z",
    "reviewReply": {
      "comment": "Hola Fatima!  Muchas gracias por calificarnos!!  Te esperamos de vuelta pronto!!",
      "updateTime": "2026-01-09T19:08:37.084796Z"
    },
    "name": "accounts/109853746269412609224/locations/5256422588388150484/reviews/Ci9DQUlRQUNvZENodHljRjlvT21WelMxQTBSVEJ4U1VkNE0xZG9aakp5ZURkQ1pWRRAB"
  }, {
    "reviewer": {
      "displayName": "Julio Germán Gómez"
    },
    "starRating": "FIVE",
    "createTime": "2026-01-07T12:36:51.067867Z",
    "updateTime": "2026-01-07T12:36:51.067867Z",
    "reviewReply": {
      "comment": "Hola Julio! Muchas gracias por calificarnos!! Te esperamos de vuelta pronto!!",
      "updateTime": "2026-01-09T19:08:50.635264Z"
    },
    "name": "accounts/109853746269412609224/locations/5256422588388150484/reviews/Ci9DQUlRQUNvZENodHljRjlvT25neWFHVTNTVlF0WXpKRVdVRjNVRGhKVW1zemVWRRAB"
  }, {
    "reviewer": {
      "displayName": "patricia martire"
    },
    "starRating": "FIVE",
    "comment": "Todo super! La atención genial\n\n(Translated by Google)\nEverything was great! The service was fantastic.",
    "createTime": "2026-01-06T18:28:57.816510Z",
    "updateTime": "2026-01-06T18:28:57.816510Z",
    "reviewReply": {
      "comment": "Hola Patricia! Muchas gracias por tu comentario!! Te esperamos de vuelta pronto!!",
      "updateTime": "2026-01-09T19:09:15.692418Z"
    },
    "name": "accounts/109853746269412609224/locations/5256422588388150484/reviews/Ci9DQUlRQUNvZENodHljRjlvT25VMFFYZDFVR1l5Y1RkVlF6WmplblZoYjJaRVkyYxAB"
  }, {
    "reviewer": {
      "displayName": "Oscar Peña"
    },
    "starRating": "FIVE",
    "comment": "Estuve en el taller del ACA,  Realmente,  todo perfecto.  Super recomendable\n\n(Translated by Google)\nI went to the ACA workshop, and everything was perfect. Highly recommended.",
    "createTime": "2026-01-06T03:30:28.785341Z",
    "updateTime": "2026-01-06T03:30:28.785341Z",
    "reviewReply": {
      "comment": "Hola Oscar, gracias por tu comentario!!",
      "updateTime": "2026-01-06T14:56:45.252541Z"
    },
    "name": "accounts/109853746269412609224/locations/5256422588388150484/reviews/Ci9DQUlRQUNvZENodHljRjlvT2pWbVZrazFYMVZ0ZFdoV2FqSTBTREJzVkZkSVMwRRAB"
  }, {
    "reviewer": {
      "displayName": "Carlos Alvarado"
    },
    "starRating": "THREE",
    "comment": "Muy lentos para atender. Buen precio, buenos baños.\n\n(Translated by Google)\nVery slow service. Good price, nice restrooms.",
    "createTime": "2019-10-13T15:41:39.573746Z",
    "updateTime": "2026-01-06T01:59:52.171251Z",
    "reviewReply": {
      "comment": "Hola Carlos, gracias por tu comentario!  Estamos trabajando siempre para optimizar los tiempos de atención.  Saludos!",
      "updateTime": "2026-01-06T14:57:38.955405Z"
    },
    "name": "accounts/109853746269412609224/locations/5256422588388150484/reviews/ChdDSUhNMG9nS0VJQ0FnSUMwbDUzbi13RRAB"
  }, {
    "reviewer": {
      "displayName": "La Casa del Sol"
    },
    "starRating": "FIVE",
    "comment": "Súper amables todos !\n\n(Translated by Google)\nEveryone was super friendly!",
    "createTime": "2026-01-06T01:28:09.913308Z",
    "updateTime": "2026-01-06T01:28:09.913308Z",
    "reviewReply": {
      "comment": "Hola!! Gracias por tu comentario!! Te esperamos de vuelta pronto!!",
      "updateTime": "2026-01-06T14:57:58.950728Z"
    },
    "name": "accounts/109853746269412609224/locations/5256422588388150484/reviews/Ci9DQUlRQUNvZENodHljRjlvT2s1UVlXcFlhR3RwV1hKM2JtMUhRblZWVldGS1oxRRAB"
  }, {
    "reviewer": {
      "displayName": "LUCIA"
    },
    "starRating": "FIVE",
    "comment": "Muy completa, excelente servicio!!\n\n(Translated by Google)\nVery comprehensive, excellent service!!",
    "createTime": "2024-02-15T01:39:18.443248Z",
    "updateTime": "2026-01-04T19:32:25.214105Z",
    "reviewReply": {
      "comment": "Hola Lucía! Gracias por tu comentario!! Te esperamos de vuelta pronto!!",
      "updateTime": "2026-01-06T14:59:41.245091Z"
    },
    "name": "accounts/109853746269412609224/locations/5256422588388150484/reviews/ChdDSUhNMG9nS0VJQ0FnSUNkbHRXYzVRRRAB"
  }, {
    "reviewer": {
      "displayName": "A"
    },
    "starRating": "ONE",
    "comment": "Cómo puede ser que un sábado a la noche, los baños de mujer(sólo 2 habilitados)no cuenten con el esencial papel higiénico, ni personal de limpieza, como lo hay en ruta. Siendo socia espero mejoren éste servicio en todos los ACA de Caba. Increíble en plena ciudad. También deben dejar estacionar como corresponde, perpendicular al cordón y no por fuera de los conos con todos los lugares vacíos.Aclaro que aún mostrando ser socia, el personal discute estacionar como corresponde.  ¿¿¿Qué servicio brindan a los socios??👎👎👎👎👎👎👎👎👎👎👎👎👎👎👎👎👎👎👎👎Ana de Villa Crespo. Den aviso en qué susursales funcionan las oficinas de seguro, en vez de encontrarse con la sorpresa de su cierre. 👎👎👎👎👎👎👎👎Espero mejoras para publicitar al ACA, cuyas estaciones están siendo ganadas por la competencia.Gracias. 1° semana de enero/2026\n\n(Translated by Google)\nHow is it possible that on a Saturday night, the women\u0027s restrooms (only two are open) don\u0027t have essential toilet paper or cleaning staff, unlike on highways? As a member, I expect this service to improve at all ACA branches in Buenos Aires. Unbelievable, especially in the city center. They should also allow proper parking, perpendicular to the curb, not outside the cones with all the spaces empty. I should clarify that even when I show my membership number, the staff argues about parking correctly. What kind of service do they provide to members? 👎👎👎👎👎👎👎👎👎👎👎👎👎👎👎👎👎👎👎👎👎👎 Ana from Villa Crespo. Please inform members which branches have insurance offices, instead of being surprised to find them closed. 👎👎👎👎👎👎👎👎I expect improvements in advertising for the ACA, whose stations are being taken over by the competition. Thank you. 1st week of January/2026",
    "createTime": "2026-01-04T19:13:52.046694Z",
    "updateTime": "2026-01-04T19:23:35.147958Z",
    "reviewReply": {
      "comment": "Estimada socia, desde ya le pedimos disculpas por lo ocurrido.  Respecto a los baños, trabajamos para que estén en excelentes condiciones siempre, contando con personal encargado del mismo prácticamente todo el día, pero nos es muy dificultoso tener recursos para los mismos las 24 hs.  Igualmente buscamos que durante la noche los mismos estén igualmente abastecidos con todos los insumos.  Trabajaremos para que esto pueda cumplirse siempre.  Respecto al estacionamiento, efectivamente cuando hay espacios libres no hay razón para que no pueda accedes a los mismos, también lo trabajaremos con la empresa de seguridad para que no vuelva a ocurrir.  Desde ya agradecemos sus comentarios que nos a yudan siempre a mejorar! Saludos!",
      "updateTime": "2026-01-06T14:55:07.879871Z"
    },
    "name": "accounts/109853746269412609224/locations/5256422588388150484/reviews/Ci9DQUlRQUNvZENodHljRjlvT2pZM1pXcFNkbmhuZVU5dFJWVm9kR2wwWW5BeFpXYxAB"
  }, {
    "reviewer": {
      "displayName": "Hugo sebastian Romero"
    },
    "starRating": "FIVE",
    "createTime": "2026-01-04T03:06:27.013897Z",
    "updateTime": "2026-01-04T03:06:27.013897Z",
    "reviewReply": {
      "comment": "Hola Hugo! Gracias por tu calificación!! Te esperamos de vuelta pronto!!",
      "updateTime": "2026-01-06T15:00:22.153930Z"
    },
    "name": "accounts/109853746269412609224/locations/5256422588388150484/reviews/Ci9DQUlRQUNvZENodHljRjlvT21relRFSlRZamd0Tm5WUlJYUXlXVFJuWWw5dWNIYxAB"
  }, {
    "reviewer": {
      "displayName": "Marcelo Ruben Fiora"
    },
    "starRating": "FIVE",
    "comment": "Muy amable el personal\n\n(Translated by Google)\nThe staff were very friendly.",
    "createTime": "2026-01-03T12:26:08.155022Z",
    "updateTime": "2026-01-03T12:26:08.155022Z",
    "reviewReply": {
      "comment": "Hola Marcelo! Gracias por tu comentario!! Te esperamos de vuelta pronto!!",
      "updateTime": "2026-01-06T15:00:45.349735Z"
    },
    "name": "accounts/109853746269412609224/locations/5256422588388150484/reviews/Ci9DQUlRQUNvZENodHljRjlvT2tGR09XVTVSMFl0YTA5VmFqWkNORVI2UjNCMVFXYxAB"
  }, {
    "reviewer": {
      "displayName": "toni simi"
    },
    "starRating": "FOUR",
    "createTime": "2026-01-01T22:48:17.223459Z",
    "updateTime": "2026-01-01T22:48:17.223459Z",
    "reviewReply": {
      "comment": "Hola Toni!  Gracias por calificarnos!! Te esperamos de vuelta pronto!!",
      "updateTime": "2026-01-06T15:01:10.786081Z"
    },
    "name": "accounts/109853746269412609224/locations/5256422588388150484/reviews/Ci9DQUlRQUNvZENodHljRjlvT25WblFtTmxVMWhQZUVGNU9WUjFUV2hhT1RKR01HYxAB"
  }, {
    "reviewer": {
      "displayName": "Toto"
    },
    "starRating": "TWO",
    "comment": "$40.500 por un lavado completo que de completo no tiene nada. Por adentro estuvieron menos de 10 minutos y no limpiaron nada, por afuera lo mismo. Adjunto fotos. Una pérdida de plata y de tiempo.\n\n(Translated by Google)\n$40,500 for a \"complete\" wash that was anything but. They spent less than 10 minutes inside and didn\u0027t clean a thing, and the same went for the outside. Photos attached. A waste of money and time.",
    "createTime": "2025-12-30T23:37:37.954317Z",
    "updateTime": "2025-12-30T23:37:37.954317Z",
    "reviewReply": {
      "comment": "Hola Toto!  Lamentamos mucho lo ocurrido!!  Estamos trabajando para optimizar cada vez más es servicio de terminaciones.  Te invitamos a que vuelvas para recibir un lavado sin cargo.  Buscá al encargado del sector y mencioná este comentario.  Te esperamos pronto!  Saludos!",
      "updateTime": "2026-01-06T15:07:03.238009Z"
    },
    "name": "accounts/109853746269412609224/locations/5256422588388150484/reviews/Ci9DQUlRQUNvZENodHljRjlvT2t0VWJ6TjVWVTU2UVcxbE1IRlZaM2hsY1hobFJYYxAB"
  }, {
    "reviewer": {
      "displayName": "Jesus Brito"
    },
    "starRating": "FIVE",
    "createTime": "2025-12-30T12:32:07.411747Z",
    "updateTime": "2025-12-30T12:32:07.411747Z",
    "reviewReply": {
      "comment": "Hola Jesus!  Gracias por calificarnos!  Te esperamos de vuelta pronto!!",
      "updateTime": "2026-01-06T15:07:31.265520Z"
    },
    "name": "accounts/109853746269412609224/locations/5256422588388150484/reviews/Ci9DQUlRQUNvZENodHljRjlvT2taaWEzcEhhbTFuZGtOZmNtTkViV054YmxWMGFrRRAB"
  }]
}