{
  "reviews": [{
    "reviewer": {
      "displayName": "Joaquin Trillo"
    },
    "starRating": "FOUR",
    "createTime": "2017-12-02T22:12:14.835Z",
    "updateTime": "2017-12-02T22:12:14.835Z",
    "name": "accounts/109853746269412609224/locations/2813003656748655180/reviews/ChdDSUhNMG9nS0VJQ0FnSUNBd2ZtWWtnRRAB"
  }, {
    "reviewer": {
      "displayName": "Martín Hussein"
    },
    "starRating": "FIVE",
    "createTime": "2017-12-02T15:39:50.675Z",
    "updateTime": "2017-12-02T15:39:50.675Z",
    "name": "accounts/109853746269412609224/locations/2813003656748655180/reviews/ChdDSUhNMG9nS0VJQ0FnSURRc2RQT3VBRRAB"
  }, {
    "reviewer": {
      "displayName": "Pablo Russo"
    },
    "starRating": "FIVE",
    "comment": "Un 10 la atención\n\n(Translated by Google)\nThe service was a 10 out of 10.",
    "createTime": "2017-12-02T15:07:48.348Z",
    "updateTime": "2017-12-02T15:08:04.390Z",
    "name": "accounts/109853746269412609224/locations/2813003656748655180/reviews/ChdDSUhNMG9nS0VJQ0FnSUNBcTZmX29BRRAB"
  }, {
    "reviewer": {
      "displayName": "Jorge Braggio"
    },
    "starRating": "THREE",
    "createTime": "2017-12-02T13:53:50.452Z",
    "updateTime": "2017-12-02T13:53:50.452Z",
    "name": "accounts/109853746269412609224/locations/2813003656748655180/reviews/ChZDSUhNMG9nS0VJQ0FnSURRaXBiVU9REAE"
  }, {
    "reviewer": {
      "displayName": "Jesica Billia"
    },
    "starRating": "FOUR",
    "comment": "Excelente para descansar las piernas\n\n(Translated by Google)\nExcellent for resting your legs",
    "createTime": "2017-12-02T03:22:29.909Z",
    "updateTime": "2017-12-02T03:22:41.020Z",
    "name": "accounts/109853746269412609224/locations/2813003656748655180/reviews/ChZDSUhNMG9nS0VJQ0FnSURRNXQ3WlVBEAE"
  }, {
    "reviewer": {
      "displayName": "Gonzalo Tavela"
    },
    "starRating": "TWO",
    "createTime": "2017-12-02T02:09:31.556Z",
    "updateTime": "2017-12-02T02:09:31.658Z",
    "name": "accounts/109853746269412609224/locations/2813003656748655180/reviews/ChdDSUhNMG9nS0VJQ0FnSUNnN1BPajRBRRAB"
  }, {
    "reviewer": {
      "displayName": "silvana berman"
    },
    "starRating": "FIVE",
    "comment": "Tienen de todo para in descanso en la ruta\n\n(Translated by Google)\nThey have everything you need for a rest on the road",
    "createTime": "2017-12-02T00:14:47.757Z",
    "updateTime": "2017-12-02T00:15:25Z",
    "name": "accounts/109853746269412609224/locations/2813003656748655180/reviews/ChZDSUhNMG9nS0VJQ0FnSURnczdhU0ZREAE"
  }, {
    "reviewer": {
      "displayName": "Guillermo Sturlini"
    },
    "starRating": "FOUR",
    "createTime": "2017-12-01T16:31:49.724Z",
    "updateTime": "2017-12-01T16:31:49.724Z",
    "name": "accounts/109853746269412609224/locations/2813003656748655180/reviews/ChdDSUhNMG9nS0VJQ0FnSUNBM3FyaGhRRRAB"
  }, {
    "reviewer": {
      "displayName": "Gonzalo Prieto"
    },
    "starRating": "THREE",
    "createTime": "2017-12-01T04:31:01.827Z",
    "updateTime": "2017-12-01T04:31:01.827Z",
    "name": "accounts/109853746269412609224/locations/2813003656748655180/reviews/ChZDSUhNMG9nS0VJQ0FnSUNBLW9IbktBEAE"
  }, {
    "reviewer": {
      "displayName": "claudio rey"
    },
    "starRating": "FIVE",
    "comment": "Excelente para hacer un alto en el camino.\n\n(Translated by Google)\nExcellent for taking a break along the way.",
    "createTime": "2017-12-01T03:35:21.203Z",
    "updateTime": "2017-12-01T03:35:57.686Z",
    "name": "accounts/109853746269412609224/locations/2813003656748655180/reviews/ChdDSUhNMG9nS0VJQ0FnSUNRMDZfSmtnRRAB"
  }, {
    "reviewer": {
      "displayName": "Walter Randazzo"
    },
    "starRating": "FOUR",
    "createTime": "2017-12-01T02:51:23.927Z",
    "updateTime": "2017-12-01T02:51:23.927Z",
    "name": "accounts/109853746269412609224/locations/2813003656748655180/reviews/ChZDSUhNMG9nS0VJQ0FnSUNBMFpmVUZ3EAE"
  }, {
    "reviewer": {
      "displayName": "Juan Deverill"
    },
    "starRating": "FIVE",
    "comment": "Buen lugar para hacer una parada en la ruta 2\n\n(Translated by Google)\nGood place to stop on Route 2",
    "createTime": "2017-11-30T23:40:39.513Z",
    "updateTime": "2017-11-30T23:41:04.594Z",
    "name": "accounts/109853746269412609224/locations/2813003656748655180/reviews/ChZDSUhNMG9nS0VJQ0FnSUNnbXZuT1FnEAE"
  }, {
    "reviewer": {
      "displayName": "Marcelo Fernando Fabian Melo"
    },
    "starRating": "FIVE",
    "comment": "Fabuloso lugar para descansar en especial si la autovía está muy congestionada.\n\n(Translated by Google)\nFabulous place to rest, especially if the highway is very congested.",
    "createTime": "2017-11-30T19:32:18.388Z",
    "updateTime": "2017-11-30T19:33:07.529Z",
    "name": "accounts/109853746269412609224/locations/2813003656748655180/reviews/ChZDSUhNMG9nS0VJQ0FnSURBMEttQ01REAE"
  }, {
    "reviewer": {
      "displayName": "eduardo oscar alemano"
    },
    "starRating": "THREE",
    "createTime": "2017-11-30T18:16:53.224Z",
    "updateTime": "2017-11-30T18:16:53.224Z",
    "name": "accounts/109853746269412609224/locations/2813003656748655180/reviews/ChZDSUhNMG9nS0VJQ0FnSURnN2FmdE5REAE"
  }, {
    "reviewer": {
      "displayName": "Silvia Di Biase"
    },
    "starRating": "THREE",
    "comment": "Muy lindo parque\n\n(Translated by Google)\nVery nice park",
    "createTime": "2017-11-30T16:54:51.493Z",
    "updateTime": "2017-11-30T16:55:04.389Z",
    "name": "accounts/109853746269412609224/locations/2813003656748655180/reviews/ChdDSUhNMG9nS0VJQ0FnSUNReDdTRGx3RRAB"
  }, {
    "reviewer": {
      "displayName": "Eduardo Rocha"
    },
    "starRating": "FOUR",
    "comment": "Buen lugar..\n\n(Translated by Google)\nGood place.",
    "createTime": "2017-11-30T11:27:02.360Z",
    "updateTime": "2017-11-30T11:27:20.979Z",
    "name": "accounts/109853746269412609224/locations/2813003656748655180/reviews/ChdDSUhNMG9nS0VJQ0FnSURnbWJQeHhnRRAB"
  }, {
    "reviewer": {
      "displayName": "Hemilce Motte"
    },
    "starRating": "ONE",
    "createTime": "2017-11-30T10:39:21.057Z",
    "updateTime": "2017-11-30T10:39:21.057Z",
    "name": "accounts/109853746269412609224/locations/2813003656748655180/reviews/ChZDSUhNMG9nS0VJQ0FnSURRZzR5YVdREAE"
  }, {
    "reviewer": {
      "displayName": "//"
    },
    "starRating": "FOUR",
    "comment": "Es la nejor a la ida a Bs As\n\n(Translated by Google)\nIt is the best way to go to Buenos Aires.",
    "createTime": "2017-11-30T10:31:16.197Z",
    "updateTime": "2017-11-30T10:31:43.951Z",
    "name": "accounts/109853746269412609224/locations/2813003656748655180/reviews/ChdDSUhNMG9nS0VJQ0FnSURBMzZqTjFBRRAB"
  }, {
    "reviewer": {
      "displayName": "Pablo Ignacio Bazzola"
    },
    "starRating": "FOUR",
    "createTime": "2017-11-30T09:52:24.613Z",
    "updateTime": "2017-11-30T09:52:24.613Z",
    "name": "accounts/109853746269412609224/locations/2813003656748655180/reviews/ChZDSUhNMG9nS0VJQ0FnSUN3bWVlRk9nEAE"
  }, {
    "reviewer": {
      "displayName": "Federico Pagani"
    },
    "starRating": "FIVE",
    "comment": "Todo muy limpio y ordenado la comida está bastante bien el pasto cortado los baños limpios y muchas opciones para comer\n\n(Translated by Google)\nEverything was very clean and tidy, the food was quite good, the grass was cut, the bathrooms were clean, and there were many options for eating.",
    "createTime": "2017-11-30T02:06:25.469Z",
    "updateTime": "2017-11-30T02:07:01.993Z",
    "name": "accounts/109853746269412609224/locations/2813003656748655180/reviews/ChdDSUhNMG9nS0VJQ0FnSUNRLW9pNTlBRRAB"
  }]
}