{
  "reviews": [{
    "reviewer": {
      "displayName": "Rocío Lila Kaplan"
    },
    "starRating": "THREE",
    "createTime": "2017-04-16T18:48:29.831Z",
    "updateTime": "2017-04-16T18:48:29.831Z",
    "name": "accounts/109853746269412609224/locations/1103205321495883631/reviews/ChZDSUhNMG9nS0VJQ0FnSUNneGVLN2ZnEAE"
  }, {
    "reviewer": {
      "displayName": "javier gauna"
    },
    "starRating": "FOUR",
    "createTime": "2017-04-13T23:35:11.193Z",
    "updateTime": "2017-04-13T23:35:11.193Z",
    "name": "accounts/109853746269412609224/locations/1103205321495883631/reviews/ChZDSUhNMG9nS0VJQ0FnSUNRblphRlJBEAE"
  }, {
    "reviewer": {
      "displayName": "Anibal Carrizo"
    },
    "starRating": "FIVE",
    "comment": "Buen atención!\n\n(Translated by Google)\nGreat service!",
    "createTime": "2017-04-13T12:32:57.857Z",
    "updateTime": "2017-04-13T12:33:07.068Z",
    "name": "accounts/109853746269412609224/locations/1103205321495883631/reviews/ChZDSUhNMG9nS0VJQ0FnSUNneHRPbFpBEAE"
  }, {
    "reviewer": {
      "displayName": "Emiliano Leotta"
    },
    "starRating": "THREE",
    "comment": "Parada obligada hacia Colon\n\n(Translated by Google)\nObligatory stop towards Colon",
    "createTime": "2017-04-12T13:02:00.648Z",
    "updateTime": "2017-04-12T13:02:15.283Z",
    "name": "accounts/109853746269412609224/locations/1103205321495883631/reviews/ChZDSUhNMG9nS0VJQ0FnSURnckphakNnEAE"
  }, {
    "reviewer": {
      "displayName": "Gabriela Rodriguez"
    },
    "starRating": "FIVE",
    "comment": "Muy buena atención\n\n(Translated by Google)\nVery good service",
    "createTime": "2017-04-11T16:14:07.828Z",
    "updateTime": "2017-04-11T16:14:15.268Z",
    "name": "accounts/109853746269412609224/locations/1103205321495883631/reviews/ChZDSUhNMG9nS0VJQ0FnSURBbVpQTkN3EAE"
  }, {
    "reviewer": {
      "displayName": "alicia rivadero"
    },
    "starRating": "FIVE",
    "createTime": "2017-04-11T16:06:20.781Z",
    "updateTime": "2017-04-11T16:06:20.781Z",
    "name": "accounts/109853746269412609224/locations/1103205321495883631/reviews/ChZDSUhNMG9nS0VJQ0FnSUNRek1PdFdREAE"
  }, {
    "reviewer": {
      "displayName": "Claudio Ceceri"
    },
    "starRating": "FOUR",
    "comment": "Buena atencion\n\n(Translated by Google)\nGood service",
    "createTime": "2017-04-11T13:24:18.698Z",
    "updateTime": "2017-04-11T13:24:26.800Z",
    "name": "accounts/109853746269412609224/locations/1103205321495883631/reviews/ChZDSUhNMG9nS0VJQ0FnSURRMk16dkZ3EAE"
  }, {
    "reviewer": {
      "displayName": "Bruno Bordón"
    },
    "starRating": "FOUR",
    "comment": "Buena estación\n\n(Translated by Google)\nGood season",
    "createTime": "2017-04-04T22:52:16.927Z",
    "updateTime": "2017-04-04T22:52:30.482Z",
    "name": "accounts/109853746269412609224/locations/1103205321495883631/reviews/ChdDSUhNMG9nS0VJQ0FnSUNBaUlHMzFnRRAB"
  }, {
    "reviewer": {
      "displayName": "Jwhsbsna Gshbzns"
    },
    "starRating": "FOUR",
    "comment": "buen lugar\n\n(Translated by Google)\ngood place",
    "createTime": "2017-04-04T11:16:41.214Z",
    "updateTime": "2017-04-04T11:16:53.303Z",
    "name": "accounts/109853746269412609224/locations/1103205321495883631/reviews/ChZDSUhNMG9nS0VJQ0FnSURRdktYdlpBEAE"
  }, {
    "reviewer": {
      "displayName": "Elsa Figueredo"
    },
    "starRating": "FOUR",
    "comment": "Muy buena la limpieza, muy accesible\n\n(Translated by Google)\nVery clean, very accessible",
    "createTime": "2017-04-03T12:10:32.965Z",
    "updateTime": "2017-04-03T12:11:07.113Z",
    "name": "accounts/109853746269412609224/locations/1103205321495883631/reviews/ChZDSUhNMG9nS0VJQ0FnSUNRazREd2FBEAE"
  }, {
    "reviewer": {
      "displayName": "NÁUTICA COLÓN"
    },
    "starRating": "FIVE",
    "createTime": "2017-03-29T16:13:39.820Z",
    "updateTime": "2017-03-29T16:13:39.820Z",
    "name": "accounts/109853746269412609224/locations/1103205321495883631/reviews/ChZDSUhNMG9nS0VJQ0FnSUNnLXFlaUhREAE"
  }, {
    "reviewer": {
      "displayName": "Jorge Washington Barrientos"
    },
    "starRating": "FOUR",
    "createTime": "2017-03-28T17:46:01.483Z",
    "updateTime": "2017-03-28T17:46:01.483Z",
    "name": "accounts/109853746269412609224/locations/1103205321495883631/reviews/ChdDSUhNMG9nS0VJQ0FnSURRdU1LZTN3RRAB"
  }, {
    "reviewer": {
      "displayName": "Alberto Godoy"
    },
    "starRating": "FIVE",
    "comment": "Una de las pocas estaciones de las cuales el combustible no está rebajado, cada vez que vengo del litoral y cargo en cualquier otra el filtro de nafta con agua siempre. A estar atentos!\n\n(Translated by Google)\nOne of the few stations where the fuel isn\u0027t watered down. Every time I come from the coast and fill up at any other station, the fuel filter always gets clogged with water. Be careful!",
    "createTime": "2017-03-26T02:39:17.143Z",
    "updateTime": "2017-03-26T02:40:12.506Z",
    "name": "accounts/109853746269412609224/locations/1103205321495883631/reviews/ChdDSUhNMG9nS0VJQ0FnSUNRX2I3aDNRRRAB"
  }, {
    "reviewer": {
      "displayName": "Luis Laurenz"
    },
    "starRating": "THREE",
    "comment": "Buena atención\nFalta espacio en el shop\n\n(Translated by Google)\nGood service.\nThe shop is too small.",
    "createTime": "2017-03-25T13:49:10.811Z",
    "updateTime": "2017-03-25T13:51:19.857Z",
    "name": "accounts/109853746269412609224/locations/1103205321495883631/reviews/ChZDSUhNMG9nS0VJQ0FnSUNnNWEtN1dBEAE"
  }, {
    "reviewer": {
      "displayName": "Christian Fariñas"
    },
    "starRating": "THREE",
    "createTime": "2017-03-20T13:06:33.058Z",
    "updateTime": "2017-03-20T13:06:33.058Z",
    "name": "accounts/109853746269412609224/locations/1103205321495883631/reviews/ChdDSUhNMG9nS0VJQ0FnSUNnMC1MZHdRRRAB"
  }, {
    "reviewer": {
      "displayName": "Gilberto Muncinelli"
    },
    "starRating": "FOUR",
    "createTime": "2017-03-20T09:39:37.094Z",
    "updateTime": "2017-03-20T09:39:37.094Z",
    "name": "accounts/109853746269412609224/locations/1103205321495883631/reviews/ChdDSUhNMG9nS0VJQ0FnSUNBeDQ2cTNRRRAB"
  }, {
    "reviewer": {
      "displayName": "Adrian Seldes"
    },
    "starRating": "THREE",
    "createTime": "2017-03-19T02:34:55.658Z",
    "updateTime": "2017-03-19T02:34:55.658Z",
    "name": "accounts/109853746269412609224/locations/1103205321495883631/reviews/ChZDSUhNMG9nS0VJQ0FnSUNBanZHaUdnEAE"
  }, {
    "reviewer": {
      "displayName": "Daniel Morales"
    },
    "starRating": "FOUR",
    "createTime": "2017-03-12T23:50:22.407Z",
    "updateTime": "2017-03-12T23:50:22.407Z",
    "name": "accounts/109853746269412609224/locations/1103205321495883631/reviews/ChZDSUhNMG9nS0VJQ0FnSUN3a3ZXNGF3EAE"
  }, {
    "reviewer": {
      "displayName": "Alejandro Pascaner"
    },
    "starRating": "FOUR",
    "createTime": "2017-03-07T00:51:50.874Z",
    "updateTime": "2017-03-07T00:51:50.874Z",
    "name": "accounts/109853746269412609224/locations/1103205321495883631/reviews/ChZDSUhNMG9nS0VJQ0FnSUNBZzhfSmV3EAE"
  }, {
    "reviewer": {
      "displayName": "Dario Escobar"
    },
    "starRating": "FOUR",
    "createTime": "2017-03-06T15:06:13.660Z",
    "updateTime": "2017-03-06T15:06:20.433Z",
    "name": "accounts/109853746269412609224/locations/1103205321495883631/reviews/ChZDSUhNMG9nS0VJQ0FnSUN3NDdlWlp3EAE"
  }]
}