{
  "reviews": [{
    "reviewer": {
      "displayName": "Victor DV"
    },
    "starRating": "FIVE",
    "createTime": "2022-06-17T15:04:58.285576Z",
    "updateTime": "2022-06-17T15:04:58.285576Z",
    "reviewReply": {
      "comment": "GRACIAS por dejarnos su clasificación.\nZambrano Combustibles S.R.L Concesionario Oficial ACA!",
      "updateTime": "2022-06-28T11:34:52.103440Z"
    },
    "name": "accounts/109853746269412609224/locations/9200897225069866922/reviews/ChdDSUhNMG9nS0VJQ0FnSUNPdlpIYnRBRRAB"
  }, {
    "reviewer": {
      "displayName": "Jorge Alberto Wolcan"
    },
    "starRating": "FIVE",
    "comment": "Todo bien\n\n(Translated by Google)\nAll good",
    "createTime": "2022-06-16T15:23:11.354418Z",
    "updateTime": "2022-06-16T15:23:11.354418Z",
    "reviewReply": {
      "comment": "GRACIAS por dejarnos su comentario.\nZambrano Combustibles S.R.L Concesionario Oficial ACA!",
      "updateTime": "2022-06-28T11:35:16.868890Z"
    },
    "name": "accounts/109853746269412609224/locations/9200897225069866922/reviews/ChZDSUhNMG9nS0VJQ0FnSUNPemVYOVZnEAE"
  }, {
    "reviewer": {
      "displayName": "Marcelo Delgadillo"
    },
    "starRating": "ONE",
    "comment": "Desastre. Vine con auto de chapa extranjera y me subieron el precio del combustible. Les mostré DNI, que soy Neuquino y nada, me fajaron...\n\n(Translated by Google)\nDisaster. I came with a car with foreign plates and they raised the price of fuel. I showed them my ID, proving I\u0027m from Neuquén, and nothing, they just ripped me off...",
    "createTime": "2022-06-14T13:55:24.676348Z",
    "updateTime": "2022-06-14T13:55:24.676348Z",
    "name": "accounts/109853746269412609224/locations/9200897225069866922/reviews/ChdDSUhNMG9nS0VJQ0FnSUNPLVpieWhRRRAB"
  }, {
    "reviewer": {
      "displayName": "Mirian Celeste Duarte Báez"
    },
    "starRating": "FIVE",
    "comment": "Buena atención, ambiente limpio y mucho más los sanitario!!! Recomendado!!!\n\n(Translated by Google)\nGreat service, clean environment, and the restrooms are fantastic!!! Highly recommended!!!",
    "createTime": "2022-06-13T03:11:52.930629Z",
    "updateTime": "2022-06-13T03:11:52.930629Z",
    "reviewReply": {
      "comment": "GRACIAS por dejarnos su comentario.\nZambrano Combustibles S.R.L Concesionario Oficial ACA!",
      "updateTime": "2022-06-28T11:35:27.192678Z"
    },
    "name": "accounts/109853746269412609224/locations/9200897225069866922/reviews/ChZDSUhNMG9nS0VJQ0FnSUNPOGN2ZEJBEAE"
  }, {
    "reviewer": {
      "displayName": "Gloria Zambrano"
    },
    "starRating": "FIVE",
    "comment": "Excelente atención y pronta respuesta a mis necesidades! Espectacular la limpieza de los baños y la playa\n\n(Translated by Google)\nExcellent service and prompt response to my needs! The bathrooms and beach were spectacularly clean.",
    "createTime": "2022-06-11T02:18:08.520558Z",
    "updateTime": "2022-06-11T02:18:08.520558Z",
    "name": "accounts/109853746269412609224/locations/9200897225069866922/reviews/ChdDSUhNMG9nS0VJQ0FnSUNPM3NHRHR3RRAB"
  }, {
    "reviewer": {
      "displayName": "Maria Leonor Lopez"
    },
    "starRating": "FOUR",
    "createTime": "2022-06-09T19:22:57.049180Z",
    "updateTime": "2022-06-09T19:22:57.049180Z",
    "reviewReply": {
      "comment": "GRACIAS por su clasificación.\nZambrano Combustibles S.R.L Concesionario Oficial ACA!",
      "updateTime": "2022-06-28T11:36:51.796124Z"
    },
    "name": "accounts/109853746269412609224/locations/9200897225069866922/reviews/ChZDSUhNMG9nS0VJQ0FnSUNPOW9uLWZ3EAE"
  }, {
    "reviewer": {
      "displayName": "Nicolas Freaza"
    },
    "starRating": "FIVE",
    "createTime": "2022-06-09T17:33:42.977825Z",
    "updateTime": "2022-06-09T17:33:42.977825Z",
    "reviewReply": {
      "comment": "GRACIAS por su clasificación.\nZambrano Combustibles S.R.L Concesionario Oficial ACA!",
      "updateTime": "2022-06-28T11:36:56.230375Z"
    },
    "name": "accounts/109853746269412609224/locations/9200897225069866922/reviews/ChdDSUhNMG9nS0VJQ0FnSUNPOXBUdW5nRRAB"
  }, {
    "reviewer": {
      "displayName": "Carlos Enrique Lanari"
    },
    "starRating": "FIVE",
    "comment": "Rapidez de servicio a pesar de la cantidad de clientes presentes.\n\n(Translated by Google)\nFast service despite the number of customers present.",
    "createTime": "2022-06-08T13:32:14.736054Z",
    "updateTime": "2022-06-08T13:32:14.736054Z",
    "reviewReply": {
      "comment": "GRACIAS por dejarnos su comentario.\nZambrano Combustibles S.R.L Concesionario Oficial ACA!",
      "updateTime": "2022-06-28T11:36:06.563802Z"
    },
    "name": "accounts/109853746269412609224/locations/9200897225069866922/reviews/ChdDSUhNMG9nS0VJQ0FnSUNPeHNhV2dRRRAB"
  }, {
    "reviewer": {
      "displayName": "treinomonster online"
    },
    "starRating": "FIVE",
    "createTime": "2022-06-07T21:12:19.890489Z",
    "updateTime": "2022-06-07T21:12:19.890489Z",
    "reviewReply": {
      "comment": "GRACIAS por su clasificación.\nZambrano Combustibles S.R.L Concesionario Oficial ACA!",
      "updateTime": "2022-06-28T11:37:07.348131Z"
    },
    "name": "accounts/109853746269412609224/locations/9200897225069866922/reviews/ChZDSUhNMG9nS0VJQ0FnSUNPdXFHZUFREAE"
  }, {
    "reviewer": {
      "displayName": "Arielpk Ok (Arielpk)"
    },
    "starRating": "FIVE",
    "createTime": "2022-06-06T14:14:04.311337Z",
    "updateTime": "2022-06-06T14:14:04.311337Z",
    "reviewReply": {
      "comment": "GRACIAS por su clasificación.\nZambrano Combustibles S.R.L Concesionario Oficial ACA!",
      "updateTime": "2022-06-28T11:37:38.778106Z"
    },
    "name": "accounts/109853746269412609224/locations/9200897225069866922/reviews/ChZDSUhNMG9nS0VJQ0FnSUNPOHBIbk9BEAE"
  }, {
    "reviewer": {
      "displayName": "Mi Viadas"
    },
    "starRating": "ONE",
    "comment": "Personal muy mal educado. Mala organización. Se arman colas en la calle\n\n(Translated by Google)\nVery rude staff. Poor organization. Queues form in the street.",
    "createTime": "2022-06-03T20:41:30.827600Z",
    "updateTime": "2022-06-03T20:41:30.827600Z",
    "name": "accounts/109853746269412609224/locations/9200897225069866922/reviews/ChdDSUhNMG9nS0VJQ0FnSUNPclBmNDFRRRAB"
  }, {
    "reviewer": {
      "displayName": "Camila Gomez"
    },
    "starRating": "FIVE",
    "createTime": "2022-06-02T20:01:23.857402Z",
    "updateTime": "2022-06-02T20:01:23.857402Z",
    "reviewReply": {
      "comment": "GRACIAS por su clasificación.\nZambrano Combustibles S.R.L Concesionario Oficial ACA!",
      "updateTime": "2022-06-28T11:37:45.418321Z"
    },
    "name": "accounts/109853746269412609224/locations/9200897225069866922/reviews/ChdDSUhNMG9nS0VJQ0FnSUNPdExTeTBnRRAB"
  }, {
    "reviewer": {
      "displayName": "Luis Zariaga"
    },
    "starRating": "FIVE",
    "createTime": "2022-05-30T00:24:52.342004Z",
    "updateTime": "2022-05-30T00:24:52.342004Z",
    "reviewReply": {
      "comment": "GRACIAS por su clasificación.\nZambrano Combustibles S.R.L Concesionario Oficial ACA!",
      "updateTime": "2022-06-28T11:37:49.695143Z"
    },
    "name": "accounts/109853746269412609224/locations/9200897225069866922/reviews/ChZDSUhNMG9nS0VJQ0FnSUNPd05Yd2JBEAE"
  }, {
    "reviewer": {
      "displayName": "maximiliano pianovi"
    },
    "starRating": "FIVE",
    "comment": "Excelente  atencion y servicio  super recomendable\n\n(Translated by Google)\nExcellent attention and service, highly recommended",
    "createTime": "2022-05-28T21:06:15.130538Z",
    "updateTime": "2022-05-28T21:06:15.130538Z",
    "name": "accounts/109853746269412609224/locations/9200897225069866922/reviews/ChZDSUhNMG9nS0VJQ0FnSUQyci0yeUxREAE"
  }, {
    "reviewer": {
      "displayName": "Juan Carlos Bogado"
    },
    "starRating": "FIVE",
    "comment": "Es mí lugar preferido para cargar NAFTA\nBuena atención\n\n(Translated by Google)\nIt\u0027s my favorite place to fill up with gas.\nGreat service.",
    "createTime": "2022-05-28T14:49:13.035077Z",
    "updateTime": "2022-05-28T14:49:13.035077Z",
    "reviewReply": {
      "comment": "GRACIAS por dejarnos su comentario.\nZambrano Combustibles S.R.L Concesionario Oficial ACA!",
      "updateTime": "2022-06-28T11:35:45.521945Z"
    },
    "name": "accounts/109853746269412609224/locations/9200897225069866922/reviews/ChZDSUhNMG9nS0VJQ0FnSUQyejRxSFlREAE"
  }, {
    "reviewer": {
      "displayName": "reinaldo Aguilera"
    },
    "starRating": "FIVE",
    "createTime": "2022-05-24T16:27:14.686875Z",
    "updateTime": "2022-05-24T16:27:14.686875Z",
    "reviewReply": {
      "comment": "GRACIAS por su clasificación.\nZambrano Combustibles S.R.L Concesionario Oficial ACA!",
      "updateTime": "2022-06-28T11:40:44.099233Z"
    },
    "name": "accounts/109853746269412609224/locations/9200897225069866922/reviews/ChZDSUhNMG9nS0VJQ0FnSUQyODhDR0ZnEAE"
  }, {
    "reviewer": {
      "displayName": "Natalio Dominico"
    },
    "starRating": "FIVE",
    "comment": "Atención buenos de los playeros vendedores del servi club muy amable realmente te atienden y bien y los baño muy limpio\n\n(Translated by Google)\nThe beach attendants at the service club are very friendly and helpful, and the restrooms are very clean.",
    "createTime": "2022-05-20T15:51:44.351771Z",
    "updateTime": "2022-05-20T15:51:44.351771Z",
    "name": "accounts/109853746269412609224/locations/9200897225069866922/reviews/ChdDSUhNMG9nS0VJQ0FnSUQybGViN3hBRRAB"
  }, {
    "reviewer": {
      "displayName": "Sebastian Yunis"
    },
    "starRating": "TWO",
    "comment": "Siempre haciendo cola para cargar nafta y les cuesta entregar comprobante de pago\n\n(Translated by Google)\nAlways queuing to fill up with gas and they struggle to provide proof of payment.",
    "createTime": "2022-05-19T18:20:11.797931Z",
    "updateTime": "2022-05-19T18:20:11.797931Z",
    "name": "accounts/109853746269412609224/locations/9200897225069866922/reviews/ChZDSUhNMG9nS0VJQ0FnSUQyaGVxalFnEAE"
  }, {
    "reviewer": {
      "displayName": "Roberto Benitez"
    },
    "starRating": "FIVE",
    "comment": "excelente atención.\n\n(Translated by Google)\nExcellent service.",
    "createTime": "2022-05-19T12:43:48.622747Z",
    "updateTime": "2022-05-19T12:43:48.622747Z",
    "reviewReply": {
      "comment": "GRACIAS por dejarnos su comentario.\nZambrano Combustibles S.R.L Concesionario Oficial ACA!",
      "updateTime": "2022-06-28T11:40:31.644654Z"
    },
    "name": "accounts/109853746269412609224/locations/9200897225069866922/reviews/ChZDSUhNMG9nS0VJQ0FnSUQydVl1Q0FnEAE"
  }, {
    "reviewer": {
      "displayName": "Marcelo Espinoza"
    },
    "starRating": "FIVE",
    "createTime": "2022-05-17T14:17:25.745780Z",
    "updateTime": "2022-05-17T14:17:25.745780Z",
    "reviewReply": {
      "comment": "GRACIAS por su clasificación.\nZambrano Combustibles S.R.L Concesionario Oficial ACA!",
      "updateTime": "2022-06-28T11:40:50.351459Z"
    },
    "name": "accounts/109853746269412609224/locations/9200897225069866922/reviews/ChdDSUhNMG9nS0VJQ0FnSUQyMFkzWDZ3RRAB"
  }]
}